happi/__init__.py
happi/__main__.py
happi/_version.py
happi/audit.py
happi/cli.py
happi/client.py
happi/containers.py
happi/errors.py
happi/item.py
happi/loader.py
happi/prompt.py
happi/utils.py
happi/version.py
happi/backends/__init__.py
happi/backends/core.py
happi/backends/json_db.py
happi/backends/mongo_db.py
happi/backends/multi_db.py
happi/backends/qs_db.py
happi/qt/__init__.py
happi/qt/designer.py
happi/qt/happi_metadata_view.ui
happi/qt/happi_search_widget.ui
happi/qt/helpers.py
happi/qt/model.py
happi/qt/widgets.py
happi/tests/__init__.py
happi/tests/conftest.py
happi/tests/test_audit.py
happi/tests/test_backends.py
happi/tests/test_cli.py
happi/tests/test_client.py
happi/tests/test_happi_item.py
happi/tests/test_loader.py
happi/tests/test_prompt.py
happi/tests/test_qt.py
happi-3.0.0.dist-info/licenses/AUTHORS.rst
happi-3.0.0.dist-info/licenses/LICENSE.md
happi-3.0.0.dist-info/METADATA
happi-3.0.0.dist-info/WHEEL
happi-3.0.0.dist-info/entry_points.txt
happi-3.0.0.dist-info/top_level.txt
happi-3.0.0.dist-info/RECORD
