Metadata-Version: 2.4
Name: happi
Version: 3.0.0
Summary: Happi Database Access for LCLS Beamline Devices
Author: SLAC National Accelerator Laboratory
License: Copyright (c) 2023, The Board of Trustees of the Leland Stanford Junior
Classifier: Development Status :: 2 - Pre-Alpha
Classifier: Natural Language :: English
Classifier: Programming Language :: Python :: 3
Requires-Python: >=3.9
License-File: LICENSE.md
License-File: AUTHORS.rst
Requires-Dist: click
Requires-Dist: jinja2
Requires-Dist: simplejson
Requires-Dist: platformdirs
Requires-Dist: prettytable
Requires-Dist: coloredlogs
Requires-Dist: entrypoints
Provides-Extra: gui
Requires-Dist: PyQt5; extra == "gui"
Requires-Dist: qtpy; extra == "gui"
Provides-Extra: mongo
Requires-Dist: pymongo; extra == "mongo"
Provides-Extra: test
Requires-Dist: pytest; extra == "test"
Requires-Dist: pytest-cov; extra == "test"
Requires-Dist: pytest-qt; extra == "test"
Requires-Dist: ipython; extra == "test"
Requires-Dist: matplotlib>=3.2.0; extra == "test"
Requires-Dist: ophyd>=1.5.0; extra == "test"
Requires-Dist: pcdsutils; extra == "test"
Requires-Dist: pcdsdevices; extra == "test"
Requires-Dist: mongomock>=3.22.0; extra == "test"
Requires-Dist: line_profiler; extra == "test"
Requires-Dist: PyQt5; extra == "test"
Requires-Dist: qtpy; extra == "test"
Requires-Dist: pymongo; extra == "test"
Provides-Extra: doc
Requires-Dist: docs-versions-menu; extra == "doc"
Requires-Dist: doctr; extra == "doc"
Requires-Dist: sphinx; extra == "doc"
Requires-Dist: sphinx_rtd_theme>=1.2.0; extra == "doc"
Requires-Dist: sphinx-click; extra == "doc"
Requires-Dist: sphinxcontrib-jquery; extra == "doc"
Provides-Extra: all
Requires-Dist: PyQt5; extra == "all"
Requires-Dist: qtpy; extra == "all"
Requires-Dist: pymongo; extra == "all"
Dynamic: license-file
